flask2neo4j/__init__.py
Flask2Neo4J-0.1a1.dist-info/LICENSE
Flask2Neo4J-0.1a1.dist-info/METADATA
Flask2Neo4J-0.1a1.dist-info/WHEEL
Flask2Neo4J-0.1a1.dist-info/top_level.txt
Flask2Neo4J-0.1a1.dist-info/RECORD
