Metadata-Version: 2.1
Name: Flask2Neo4J
Version: 0.1a1
Summary: Extension Flask for integration with neo4j graph database
Home-page: https://github.com/ganggas95/flask2neo4j
Author: Ganggas95
Author-email: subhannizar25@amail.com
License: MIT
Platform: UNKNOWN
Classifier: Programming Language :: Python :: 3
Classifier: License :: OSI Approved :: MIT License
Classifier: Operating System :: OS Independent
Classifier: Topic :: Software Development :: Libraries :: Python Modules
Classifier: Topic :: Database
Requires-Dist: Flask (>=1.0)
Requires-Dist: py2neo (>=3.0)
Requires-Dist: prompt-toolkit (<2.1,>=2.0.7)
